LICENSE
README.md
setup.py
npp_2d_truss_analysis/__init__.py
npp_2d_truss_analysis/truss_analysis_2d.py
npp_2d_truss_analysis/truss_input.py
npp_2d_truss_analysis/truss_plotter.py
npp_2d_truss_analysis/truss_project.py
npp_2d_truss_analysis/truss_solution.py
npp_2d_truss_analysis.egg-info/PKG-INFO
npp_2d_truss_analysis.egg-info/SOURCES.txt
npp_2d_truss_analysis.egg-info/dependency_links.txt
npp_2d_truss_analysis.egg-info/requires.txt
npp_2d_truss_analysis.egg-info/top_level.txt
tests/test_forces_input.py
tests/test_input.py
tests/test_input_json.py
tests/test_mesh.py
tests/test_truss_plotter.py